{"cameraMode":{"drawMode":0,"name":"Shaded","section":"Shading Mode"},"sceneLighting":false,"audioPlay":false,"sceneViewState":{"showFog":true,"showMaterialUpdate":false,"showSkybox":false,"showFlares":true,"showImageEffects":true,"showParticleSystems":true,"showVisualEffectGraphs":true,"m_FxEnabled":true},"in2DMode":false,"pivot":{"x":-0.6781455278396606,"y":5.268101692199707,"z":-0.6513844132423401},"rotation":{"x":-0.19596301019191743,"y":-0.1560615748167038,"z":0.03160686418414116,"w":-0.9676649570465088},"size":1.2186554670333863,"orthographic":false}